grabclient/__init__.py
grabclient/client.py
grabclient/common.py
grabclient/constant.py
grabclient/exceptions.py
grabclient/helper.py
grabclient/requests.py
grabclient/responses.py
grabclient-1.1.10.dist-info/AUTHORS.rst
grabclient-1.1.10.dist-info/LICENSE
grabclient-1.1.10.dist-info/METADATA
grabclient-1.1.10.dist-info/WHEEL
grabclient-1.1.10.dist-info/top_level.txt
grabclient-1.1.10.dist-info/RECORD
