Metadata-Version: 2.1
Name: grabclient
Version: 1.1.10
Summary: Python library to consume GRABExpress API
Home-page: UNKNOWN
Author: Heri Priyatno
Author-email: heri.priyatno@staff.gramedia.com
License: MIT license
Keywords: grabclient
Platform: UNKNOWN
Classifier: Development Status :: 2 - Pre-Alpha
Classifier: Intended Audience :: Developers
Classifier: License :: OSI Approved :: MIT License
Classifier: Natural Language :: English
Classifier: Programming Language :: Python :: 3
Classifier: Programming Language :: Python :: 3.6
Classifier: Programming Language :: Python :: 3.7
License-File: LICENSE
License-File: AUTHORS.rst
Requires-Dist: requests
Requires-Dist: redis
